setup.cfg
setup.py
TracSQLAlchemyBridge.egg-info/PKG-INFO
TracSQLAlchemyBridge.egg-info/SOURCES.txt
TracSQLAlchemyBridge.egg-info/dependency_links.txt
TracSQLAlchemyBridge.egg-info/namespace_packages.txt
TracSQLAlchemyBridge.egg-info/requires.txt
TracSQLAlchemyBridge.egg-info/top_level.txt
tracext/__init__.py
tracext/sa/__init__.py