Metadata-Version: 1.0
Name: TracSQLAlchemyBridge
Version: 0.1.0
Summary: Bridge for a plugin developer to use SQLAlchemy with trac
Home-page: http://trac-hacks.org/wiki/TracSqlAlchemyBridgeIntegration
Author: Armin Ronacher, Pedro Algarvio
Author-email: armin.ronacher@active-4.com, ufs@ufsoft.org
License: WTFPL
Download-URL: http://python.org/pypi/TracSQLAlchemyBridge
Keywords: bridge sqlalchemy trac
Platform: OS Independent - Anywhere Python
Platform: Trac >=0.11 and SQLAlchemy is known to run.
